zcls/__init__.py
zcls/assets/__init__.py
zcls/config/__init__.py
zcls/config/key_word.py
zcls/config/configs/__init__.py
zcls/config/configs/custom_config.py
zcls/config/configs/dataloader.py
zcls/config/configs/dataset.py
zcls/config/configs/defaults.py
zcls/config/configs/lr_scheduler.py
zcls/config/configs/model.py
zcls/config/configs/optimizer.py
zcls/config/configs/transform.py
zcls/data/__init__.py
zcls/data/build.py
zcls/data/dataloader/__init__.py
zcls/data/dataloader/build.py
zcls/data/datasets/__init__.py
zcls/data/datasets/build.py
zcls/data/datasets/cifar.py
zcls/data/datasets/fashionmnist.py
zcls/data/datasets/general_dataset.py
zcls/data/datasets/general_dataset_v2.py
zcls/data/datasets/imagenet.py
zcls/data/datasets/lmdb_dataset.py
zcls/data/datasets/lmdb_imagenet.py
zcls/data/datasets/mp_dataset.py
zcls/data/datasets/util.py
zcls/data/datasets/evaluator/__init__.py
zcls/data/datasets/evaluator/base_evaluator.py
zcls/data/datasets/evaluator/general_evaluator.py
zcls/data/samplers/__init__.py
zcls/data/samplers/distributed_sampler.py
zcls/data/transforms/__init__.py
zcls/data/transforms/build.py
zcls/data/transforms/realization/__init__.py
zcls/data/transforms/realization/autoaugment.py
zcls/data/transforms/realization/center_crop.py
zcls/data/transforms/realization/coarse_dropout.py
zcls/data/transforms/realization/color_jitter.py
zcls/data/transforms/realization/horizontal_flip.py
zcls/data/transforms/realization/normalize.py
zcls/data/transforms/realization/random_crop.py
zcls/data/transforms/realization/resize.py
zcls/data/transforms/realization/rotate.py
zcls/data/transforms/realization/square_pad.py
zcls/data/transforms/realization/to_tensor.py
zcls/data/transforms/realization/vertical_flip.py
zcls/engine/__init__.py
zcls/engine/inference.py
zcls/engine/trainer.py
zcls/model/__init__.py
zcls/model/act_helper.py
zcls/model/attention_helper.py
zcls/model/conv_helper.py
zcls/model/init_helper.py
zcls/model/misc.py
zcls/model/norm_helper.py
zcls-0.15.2.dist-info/LICENSE
zcls-0.15.2.dist-info/METADATA
zcls-0.15.2.dist-info/WHEEL
zcls-0.15.2.dist-info/top_level.txt
zcls-0.15.2.dist-info/RECORD
