Metadata-Version: 2.1
Name: zcls
Version: 0.15.2
Summary: Object Classification Training/Inferring Framework 
Home-page: https://github.com/ZJCV/ZCls
Author: zj
Author-email: wy163zhuj@163.com
License: UNKNOWN
Platform: UNKNOWN
Classifier: Programming Language :: Python :: 3
Classifier: Operating System :: OS Independent
Classifier: License :: OSI Approved :: Apache Software License
Requires-Python: >=3.8
Requires-Dist: albumentations (>=1.0.3)
Requires-Dist: Pillow-SIMD (>=7.0.0.post3)
Requires-Dist: lmdb (>=1.2.1)
Requires-Dist: numpy (>=1.21.0)
Requires-Dist: opencv-python (>=4.5.3.56)
Requires-Dist: psutil (>=5.8.0)
Requires-Dist: resnest (==0.0.6b20210114)
Requires-Dist: six (>=1.16.0)
Requires-Dist: tabulate (>=0.8.7)
Requires-Dist: thop (>=0.0.31.post2005241907)
Requires-Dist: torch (>=1.10.0)
Requires-Dist: torchvision (>=0.11.1)
Requires-Dist: tqdm (>=4.56.0)
Requires-Dist: yacs (>=0.1.8)
Requires-Dist: tensorboard (>=2.5.0)
